coala_utils/Comparable.py
coala_utils/Constants.py
coala_utils/ContextManagers.py
coala_utils/Extensions.py
coala_utils/FilePathCompleter.py
coala_utils/FileUtils.py
coala_utils/MutableValue.py
coala_utils/Question.py
coala_utils/VERSION
coala_utils/__init__.py
coala_utils/decorators.py
coala_utils/param_conversion.py
coala_utils/string_processing/Core.py
coala_utils/string_processing/Filters.py
coala_utils/string_processing/InBetweenMatch.py
coala_utils/string_processing/Match.py
coala_utils/string_processing/StringConverter.py
coala_utils/string_processing/__init__.py
coala_utils-0.7.0.dist-info/DESCRIPTION.rst
coala_utils-0.7.0.dist-info/METADATA
coala_utils-0.7.0.dist-info/RECORD
coala_utils-0.7.0.dist-info/WHEEL
coala_utils-0.7.0.dist-info/metadata.json
coala_utils-0.7.0.dist-info/top_level.txt
